genegist/__main__.py
genegist/analyzer.py
genegist/data.py
genegist-0.1.5.dist-info/LICENSE
genegist-0.1.5.dist-info/METADATA
genegist-0.1.5.dist-info/WHEEL
genegist-0.1.5.dist-info/entry_points.txt
genegist-0.1.5.dist-info/RECORD
