Metadata-Version: 2.1
Name: genegist
Version: 0.1.5
Summary: Create summararies of groups of genes.
Home-page: https://github.com/aion-labs/genegist
License: Apache
Author: JJ Ben-Joseph
Author-email: jj@tensorspace.ai
Requires-Python: >3.10
Classifier: License :: Other/Proprietary License
Classifier: Programming Language :: Python :: 3
Classifier: Programming Language :: Python :: 3.11
Classifier: Programming Language :: Python :: 3.12
Requires-Dist: biopython
Requires-Dist: openai
Requires-Dist: pandas
Requires-Dist: pyarrow
Requires-Dist: sentence-transformers
Requires-Dist: tiktoken
Requires-Dist: vectorizedb
